guacapy/__init__.py
guacapy/client.py
guacapy/managers/__init__.py
guacapy/managers/active_connections.py
guacapy/managers/base.py
guacapy/managers/connection_groups.py
guacapy/managers/connections.py
guacapy/managers/permissions.py
guacapy/managers/schema.py
guacapy/managers/sharing_profiles.py
guacapy/managers/user_groups.py
guacapy/managers/users.py
guacapy/utilities.py
guacapy-1.20251014.1.dist-info/METADATA
guacapy-1.20251014.1.dist-info/WHEEL
guacapy-1.20251014.1.dist-info/licenses/LICENSE
guacapy-1.20251014.1.dist-info/RECORD
