Metadata-Version: 2.4
Name: guacapy
Version: 1.20251014.1
Summary: A Python client for the Apache Guacamole REST API
License: GPL-3.0
License-File: LICENSE
Author: Philipp Schmitt
Author-email: philipp@schmitt.co
Requires-Python: >=3.9,<4.0
Classifier: License :: OSI Approved :: GNU General Public License v3 (GPLv3)
Classifier: Programming Language :: Python :: 3
Classifier: Programming Language :: Python :: 3.9
Classifier: Programming Language :: Python :: 3.10
Classifier: Programming Language :: Python :: 3.11
Classifier: Programming Language :: Python :: 3.12
Classifier: Programming Language :: Python :: 3.13
Classifier: Programming Language :: Python :: 3.14
Requires-Dist: requests (==2.32.5)
